mansa/__init__.py
mansa/linter.py
mansa/logger.py
mansa-0.2.0.dist-info/licenses/LICENSE
mansa-0.2.0.dist-info/METADATA
mansa-0.2.0.dist-info/WHEEL
mansa-0.2.0.dist-info/entry_points.txt
mansa-0.2.0.dist-info/top_level.txt
mansa-0.2.0.dist-info/RECORD
