Metadata-Version: 2.4
Name: mansa
Version: 0.2.0
Summary: Making your CCoE happy
Author-email: Edgar Bahilo <edgar.bahilo@b2-impact.com>
License: MIT
Project-URL: Homepage, https://github.com/b2impact/mansa/tree/main
Project-URL: Repository, https://github.com/b2impact/mansa/tree/main
Keywords: linter,python,ast
Classifier: Programming Language :: Python :: 3.11
Classifier: Programming Language :: Python
Classifier: License :: OSI Approved :: MIT License
Classifier: Development Status :: 2 - Pre-Alpha
Classifier: Operating System :: Microsoft :: Windows
Classifier: Operating System :: Unix
Classifier: Topic :: Software Development
Classifier: Topic :: Scientific/Engineering
Requires-Python: >=3.9
License-File: LICENSE
Requires-Dist: toml>=0.10.2
Requires-Dist: rich>=13.7.1
Provides-Extra: dev
Requires-Dist: pytest>=8.3.2; extra == "dev"
Requires-Dist: ruff>=0.5.7; extra == "dev"
Requires-Dist: pytest-cov>=5.0.0; extra == "dev"
Dynamic: license-file
